MultiProcessMStepRegression/Reg_Step_Wise_MP.py
MultiProcessMStepRegression/Reg_Sup_Step_Wise_MP.py
MultiProcessMStepRegression/Tool.py
MultiProcessMStepRegression/__init__.py
MultiProcessMStepRegression-0.4.1.dist-info/LICENSE
MultiProcessMStepRegression-0.4.1.dist-info/METADATA
MultiProcessMStepRegression-0.4.1.dist-info/WHEEL
MultiProcessMStepRegression-0.4.1.dist-info/top_level.txt
MultiProcessMStepRegression-0.4.1.dist-info/RECORD
