Metadata-Version: 2.1
Name: MultiProcessMStepRegression
Version: 0.4.1
Summary: python多进程逐步回归。python step-wise regression with multi-processing.
Home-page: https://github.com/wangwenhao-DATA-OG/MultiProcessMStepRegression
Author: 王文皓(wangwenhao)
Author-email: DATA-OG@139.com
Classifier: Programming Language :: Python :: 3
Classifier: License :: OSI Approved :: Apache Software License
Classifier: Operating System :: OS Independent
Requires-Python: >=3.4
License-File: LICENSE
Requires-Dist: scikit-learn (>=0.20.4)
Requires-Dist: statsmodels (>=0.10.0)
